{
    "config": null,
    "episodes": [
        {
            "episode_id": "0",
            "scene_id": "data/scene_datasets/hssd-hab/scenes-uncluttered/103997643_171030747.scene_instance.json",
            "scene_dataset_config": "data/scene_datasets/hssd-hab/hssd-hab-uncluttered.scene_dataset_config.json",
            "additional_obj_config_paths": [
                "data/objects/ycb/configs/",
                "data/replica_cad/configs/objects/"
            ],
            "start_position": [
                0,
                0,
                0
            ],
            "start_rotation": [
                0,
                0,
                0,
                1
            ],
            "info": {
                "object_labels": {
                    "009_gelatin_box_:0000": "any_targets|0"
                }
            },
            "ao_states": {},
            "rigid_objs": [
                [
                    "009_gelatin_box.object_config.json",
                    [
                        [
                            0.35638,
                            -0.0151,
                            0.93422,
                            -2.46265
                        ],
                        [
                            -0.01651,
                            0.99961,
                            0.02245,
                            0.39275
                        ],
                        [
                            -0.9342,
                            -0.02342,
                            0.35599,
                            -4.05231
                        ],
                        [
                            0.0,
                            0.0,
                            0.0,
                            1.0
                        ]
                    ]
                ]
            ],
            "targets": {
                "009_gelatin_box_:0000": [
                    [
                        -0.98038,
                        0.0,
                        -0.19709,
                        -5.14609
                    ],
                    [
                        0.0,
                        1.0,
                        0.0,
                        0.48555
                    ],
                    [
                        0.19709,
                        0.0,
                        -0.98038,
                        0.36581
                    ],
                    [
                        0.0,
                        0.0,
                        0.0,
                        1.0
                    ]
                ]
            },
            "markers": [],
            "target_receptacles": [
                [
                    "abd34aacf398e2d12913c0051c3e26ecb01afdb7_:0000",
                    null
                ]
            ],
            "goal_receptacles": [
                [
                    "a3fa19dee8b4fc9ad8005d9e9d6d458e31888041_:0000",
                    null
                ]
            ],
            "name_to_receptacle": {
                "009_gelatin_box_:0000": "abd34aacf398e2d12913c0051c3e26ecb01afdb7_:0000|receptacle_mesh_abd34aacf398e2d12913c0051c3e26ecb01afdb7.0000"
            }
        },
        {
            "episode_id": "1",
            "scene_id": "data/scene_datasets/hssd-hab/scenes-uncluttered/103997643_171030747.scene_instance.json",
            "scene_dataset_config": "data/scene_datasets/hssd-hab/hssd-hab-uncluttered.scene_dataset_config.json",
            "additional_obj_config_paths": [
                "data/objects/ycb/configs/",
                "data/replica_cad/configs/objects/"
            ],
            "start_position": [
                0,
                0,
                0
            ],
            "start_rotation": [
                0,
                0,
                0,
                1
            ],
            "info": {
                "object_labels": {
                    "035_power_drill_:0000": "any_targets|0"
                }
            },
            "ao_states": {},
            "rigid_objs": [
                [
                    "035_power_drill.object_config.json",
                    [
                        [
                            0.17805,
                            0.00509,
                            0.98401,
                            -0.02757
                        ],
                        [
                            -0.00238,
                            0.99999,
                            -0.00474,
                            0.80486
                        ],
                        [
                            -0.98402,
                            -0.0015,
                            0.17806,
                            1.82644
                        ],
                        [
                            0.0,
                            0.0,
                            0.0,
                            1.0
                        ]
                    ]
                ]
            ],
            "targets": {
                "035_power_drill_:0000": [
                    [
                        0.9036,
                        0.0,
                        0.42838,
                        -0.09624
                    ],
                    [
                        0.0,
                        1.0,
                        0.0,
                        0.53335
                    ],
                    [
                        -0.42838,
                        0.0,
                        0.9036,
                        -8.64892
                    ],
                    [
                        0.0,
                        0.0,
                        0.0,
                        1.0
                    ]
                ]
            },
            "markers": [],
            "target_receptacles": [
                [
                    "a32ed32cc5693cb1ccd4792b7c3f0340cc8eda91_:0000",
                    null
                ]
            ],
            "goal_receptacles": [
                [
                    "56f36105d7bf84f7f796bd6272391e16a2e11c5c_:0000",
                    null
                ]
            ],
            "name_to_receptacle": {
                "035_power_drill_:0000": "a32ed32cc5693cb1ccd4792b7c3f0340cc8eda91_:0000|receptacle_mesh_a32ed32cc5693cb1ccd4792b7c3f0340cc8eda91.0000"
            }
        },
        {
            "episode_id": "2",
            "scene_id": "data/scene_datasets/hssd-hab/scenes-uncluttered/103997643_171030747.scene_instance.json",
            "scene_dataset_config": "data/scene_datasets/hssd-hab/hssd-hab-uncluttered.scene_dataset_config.json",
            "additional_obj_config_paths": [
                "data/objects/ycb/configs/",
                "data/replica_cad/configs/objects/"
            ],
            "start_position": [
                0,
                0,
                0
            ],
            "start_rotation": [
                0,
                0,
                0,
                1
            ],
            "info": {
                "object_labels": {
                    "054_softball_:0000": "any_targets|0"
                }
            },
            "ao_states": {},
            "rigid_objs": [
                [
                    "054_softball.object_config.json",
                    [
                        [
                            0.90534,
                            -0.06289,
                            -0.42001,
                            -5.32957
                        ],
                        [
                            0.1083,
                            0.99047,
                            0.08513,
                            1.09181
                        ],
                        [
                            0.41065,
                            -0.12256,
                            0.90352,
                            -2.24382
                        ],
                        [
                            0.0,
                            0.0,
                            0.0,
                            1.0
                        ]
                    ]
                ]
            ],
            "targets": {
                "054_softball_:0000": [
                    [
                        0.0196,
                        0.0,
                        0.99981,
                        -6.81458
                    ],
                    [
                        0.0,
                        1.0,
                        0.0,
                        0.39208
                    ],
                    [
                        -0.99981,
                        0.0,
                        0.0196,
                        -5.52117
                    ],
                    [
                        0.0,
                        0.0,
                        0.0,
                        1.0
                    ]
                ]
            },
            "markers": [],
            "target_receptacles": [
                [
                    "a93cadff07a074a9bd121bf6ef22e74572d08fd6_:0000",
                    null
                ]
            ],
            "goal_receptacles": [
                [
                    "6ac0179bc4fa54d842212a4f46c6df06e43f0385_:0002",
                    null
                ]
            ],
            "name_to_receptacle": {
                "054_softball_:0000": "a93cadff07a074a9bd121bf6ef22e74572d08fd6_:0000|receptacle_mesh_a93cadff07a074a9bd121bf6ef22e74572d08fd6.0002"
            }
        },
        {
            "episode_id": "4",
            "scene_id": "data/scene_datasets/hssd-hab/scenes-uncluttered/103997643_171030747.scene_instance.json",
            "scene_dataset_config": "data/scene_datasets/hssd-hab/hssd-hab-uncluttered.scene_dataset_config.json",
            "additional_obj_config_paths": [
                "data/objects/ycb/configs/",
                "data/replica_cad/configs/objects/"
            ],
            "start_position": [
                0,
                0,
                0
            ],
            "start_rotation": [
                0,
                0,
                0,
                1
            ],
            "info": {
                "object_labels": {
                    "003_cracker_box_:0000": "any_targets|0"
                }
            },
            "ao_states": {},
            "rigid_objs": [
                [
                    "003_cracker_box.object_config.json",
                    [
                        [
                            0.99921,
                            0.0397,
                            0.00169,
                            -8.29942
                        ],
                        [
                            -0.03968,
                            0.99917,
                            -0.00892,
                            0.88287
                        ],
                        [
                            -0.00205,
                            0.00884,
                            0.99996,
                            -0.61909
                        ],
                        [
                            0.0,
                            0.0,
                            0.0,
                            1.0
                        ]
                    ]
                ]
            ],
            "targets": {
                "003_cracker_box_:0000": [
                    [
                        0.80361,
                        0.0,
                        0.59515,
                        -5.84235
                    ],
                    [
                        0.0,
                        1.0,
                        0.0,
                        0.65642
                    ],
                    [
                        -0.59515,
                        0.0,
                        0.80361,
                        1.48505
                    ],
                    [
                        0.0,
                        0.0,
                        0.0,
                        1.0
                    ]
                ]
            },
            "markers": [],
            "target_receptacles": [
                [
                    "a32ed32cc5693cb1ccd4792b7c3f0340cc8eda91_:0001",
                    null
                ]
            ],
            "goal_receptacles": [
                [
                    "a3fa19dee8b4fc9ad8005d9e9d6d458e31888041_:0000",
                    null
                ]
            ],
            "name_to_receptacle": {
                "003_cracker_box_:0000": "a32ed32cc5693cb1ccd4792b7c3f0340cc8eda91_:0001|receptacle_mesh_a32ed32cc5693cb1ccd4792b7c3f0340cc8eda91.0000"
            }
        }
    ]
}