{
    "config": null,
    "episodes": [
        {
            "episode_id": "0",
            "scene_id": "data/scene_datasets/hssd-hab/scenes-uncluttered/104348463_171513588.scene_instance.json",
            "scene_dataset_config": "data/scene_datasets/hssd-hab/hssd-hab-uncluttered.scene_dataset_config.json",
            "additional_obj_config_paths": [
                "data/objects/ycb/configs/",
                "data/replica_cad/configs/objects/"
            ],
            "start_position": [
                0,
                0,
                0
            ],
            "start_rotation": [
                0,
                0,
                0,
                1
            ],
            "info": {
                "object_labels": {
                    "004_sugar_box_:0000": "any_targets|0"
                }
            },
            "ao_states": {},
            "rigid_objs": [
                [
                    "004_sugar_box.object_config.json",
                    [
                        [
                            0.98642,
                            -0.03459,
                            -0.16055,
                            -3.93927
                        ],
                        [
                            0.03881,
                            0.99898,
                            0.02323,
                            0.92046
                        ],
                        [
                            0.15958,
                            -0.02914,
                            0.98675,
                            -7.73772
                        ],
                        [
                            0.0,
                            0.0,
                            0.0,
                            1.0
                        ]
                    ]
                ]
            ],
            "targets": {
                "004_sugar_box_:0000": [
                    [
                        -0.87756,
                        0.0,
                        0.47947,
                        -12.73561
                    ],
                    [
                        0.0,
                        1.0,
                        0.0,
                        0.55166
                    ],
                    [
                        -0.47947,
                        0.0,
                        -0.87756,
                        -5.47468
                    ],
                    [
                        0.0,
                        0.0,
                        0.0,
                        1.0
                    ]
                ]
            },
            "markers": [],
            "target_receptacles": [
                [
                    "467413f215daba3f0a88b154b17ccd1fb7ecb48d_:0000",
                    null
                ]
            ],
            "goal_receptacles": [
                [
                    "0f0a109cb69b1f0a8785dd2f3dbd7e4cc4d53390_:0000",
                    null
                ]
            ],
            "name_to_receptacle": {
                "004_sugar_box_:0000": "467413f215daba3f0a88b154b17ccd1fb7ecb48d_:0000|receptacle_mesh_467413f215daba3f0a88b154b17ccd1fb7ecb48d.0000"
            }
        },
        {
            "episode_id": "1",
            "scene_id": "data/scene_datasets/hssd-hab/scenes-uncluttered/104348463_171513588.scene_instance.json",
            "scene_dataset_config": "data/scene_datasets/hssd-hab/hssd-hab-uncluttered.scene_dataset_config.json",
            "additional_obj_config_paths": [
                "data/objects/ycb/configs/",
                "data/replica_cad/configs/objects/"
            ],
            "start_position": [
                0,
                0,
                0
            ],
            "start_rotation": [
                0,
                0,
                0,
                1
            ],
            "info": {
                "object_labels": {
                    "051_large_clamp_:0000": "any_targets|0"
                }
            },
            "ao_states": {},
            "rigid_objs": [
                [
                    "051_large_clamp.object_config.json",
                    [
                        [
                            -0.76042,
                            0.09374,
                            0.64263,
                            -4.53933
                        ],
                        [
                            0.17395,
                            0.98277,
                            0.06248,
                            0.83047
                        ],
                        [
                            -0.6257,
                            0.1593,
                            -0.76362,
                            -4.10896
                        ],
                        [
                            0.0,
                            0.0,
                            0.0,
                            1.0
                        ]
                    ]
                ]
            ],
            "targets": {
                "051_large_clamp_:0000": [
                    [
                        0.63767,
                        0.0,
                        -0.77031,
                        -6.33732
                    ],
                    [
                        0.0,
                        1.0,
                        0.0,
                        0.73868
                    ],
                    [
                        0.77031,
                        0.0,
                        0.63767,
                        -10.37273
                    ],
                    [
                        0.0,
                        0.0,
                        0.0,
                        1.0
                    ]
                ]
            },
            "markers": [],
            "target_receptacles": [
                [
                    "4067df5c246f5cfa298939c935aaef5775284b34_:0001",
                    null
                ]
            ],
            "goal_receptacles": [
                [
                    "42641b039e4028364b75ecf755c9ee15bd762df5_:0000",
                    null
                ]
            ],
            "name_to_receptacle": {
                "051_large_clamp_:0000": "4067df5c246f5cfa298939c935aaef5775284b34_:0001|receptacle_mesh_4067df5c246f5cfa298939c935aaef5775284b34.0000"
            }
        },
        {
            "episode_id": "2",
            "scene_id": "data/scene_datasets/hssd-hab/scenes-uncluttered/104348463_171513588.scene_instance.json",
            "scene_dataset_config": "data/scene_datasets/hssd-hab/hssd-hab-uncluttered.scene_dataset_config.json",
            "additional_obj_config_paths": [
                "data/objects/ycb/configs/",
                "data/replica_cad/configs/objects/"
            ],
            "start_position": [
                0,
                0,
                0
            ],
            "start_rotation": [
                0,
                0,
                0,
                1
            ],
            "info": {
                "object_labels": {
                    "004_sugar_box_:0000": "any_targets|0"
                }
            },
            "ao_states": {},
            "rigid_objs": [
                [
                    "004_sugar_box.object_config.json",
                    [
                        [
                            0.28607,
                            -0.03449,
                            0.95759,
                            -3.91838
                        ],
                        [
                            0.03915,
                            0.99894,
                            0.02429,
                            0.92032
                        ],
                        [
                            -0.95741,
                            0.03054,
                            0.28711,
                            -7.44892
                        ],
                        [
                            0.0,
                            0.0,
                            0.0,
                            1.0
                        ]
                    ]
                ]
            ],
            "targets": {
                "004_sugar_box_:0000": [
                    [
                        0.98163,
                        0.0,
                        0.19078,
                        -5.90218
                    ],
                    [
                        0.0,
                        1.0,
                        0.0,
                        1.24042
                    ],
                    [
                        -0.19078,
                        0.0,
                        0.98163,
                        -8.77988
                    ],
                    [
                        0.0,
                        0.0,
                        0.0,
                        1.0
                    ]
                ]
            },
            "markers": [],
            "target_receptacles": [
                [
                    "467413f215daba3f0a88b154b17ccd1fb7ecb48d_:0000",
                    null
                ]
            ],
            "goal_receptacles": [
                [
                    "8994a2078b60a17205a34a19f8851ad81980aa97_:0000",
                    null
                ]
            ],
            "name_to_receptacle": {
                "004_sugar_box_:0000": "467413f215daba3f0a88b154b17ccd1fb7ecb48d_:0000|receptacle_mesh_467413f215daba3f0a88b154b17ccd1fb7ecb48d.0000"
            }
        },
        {
            "episode_id": "3",
            "scene_id": "data/scene_datasets/hssd-hab/scenes-uncluttered/104348463_171513588.scene_instance.json",
            "scene_dataset_config": "data/scene_datasets/hssd-hab/hssd-hab-uncluttered.scene_dataset_config.json",
            "additional_obj_config_paths": [
                "data/objects/ycb/configs/",
                "data/replica_cad/configs/objects/"
            ],
            "start_position": [
                0,
                0,
                0
            ],
            "start_rotation": [
                0,
                0,
                0,
                1
            ],
            "info": {
                "object_labels": {
                    "024_bowl_:0000": "any_targets|0"
                }
            },
            "ao_states": {},
            "rigid_objs": [
                [
                    "024_bowl.object_config.json",
                    [
                        [
                            0.86545,
                            0.00105,
                            0.50099,
                            -4.93617
                        ],
                        [
                            -0.06285,
                            0.99233,
                            0.10649,
                            1.09672
                        ],
                        [
                            -0.49703,
                            -0.12365,
                            0.85888,
                            -1.42925
                        ],
                        [
                            0.0,
                            0.0,
                            0.0,
                            1.0
                        ]
                    ]
                ]
            ],
            "targets": {
                "024_bowl_:0000": [
                    [
                        -0.33851,
                        0.0,
                        -0.94096,
                        -4.70744
                    ],
                    [
                        0.0,
                        1.0,
                        0.0,
                        0.81089
                    ],
                    [
                        0.94096,
                        0.0,
                        -0.33851,
                        -12.07234
                    ],
                    [
                        0.0,
                        0.0,
                        0.0,
                        1.0
                    ]
                ]
            },
            "markers": [],
            "target_receptacles": [
                [
                    "88c87a19b5e883787b5707d90545e25360594822_:0000",
                    null
                ]
            ],
            "goal_receptacles": [
                [
                    "90bb99385fc88484cb62280e60b6ac330d801f62_:0000",
                    null
                ]
            ],
            "name_to_receptacle": {
                "024_bowl_:0000": "88c87a19b5e883787b5707d90545e25360594822_:0000|receptacle_mesh_88c87a19b5e883787b5707d90545e25360594822.0000"
            }
        }
    ]
}