{
    "config": null,
    "episodes": [
        {
            "episode_id": "0",
            "scene_id": "data/scene_datasets/hssd-hab/scenes-uncluttered/102344529.scene_instance.json",
            "scene_dataset_config": "data/scene_datasets/hssd-hab/hssd-hab-uncluttered.scene_dataset_config.json",
            "additional_obj_config_paths": [
                "data/objects/ycb/configs/",
                "data/replica_cad/configs/objects/"
            ],
            "start_position": [
                0,
                0,
                0
            ],
            "start_rotation": [
                0,
                0,
                0,
                1
            ],
            "info": {
                "object_labels": {
                    "054_softball_:0000": "any_targets|0"
                }
            },
            "ao_states": {},
            "rigid_objs": [
                [
                    "054_softball.object_config.json",
                    [
                        [
                            0.98959,
                            -0.13695,
                            0.04429,
                            -5.73864
                        ],
                        [
                            0.1295,
                            0.71284,
                            -0.68927,
                            0.75847
                        ],
                        [
                            0.06283,
                            0.68783,
                            0.72315,
                            3.43441
                        ],
                        [
                            0.0,
                            0.0,
                            0.0,
                            1.0
                        ]
                    ]
                ]
            ],
            "targets": {
                "054_softball_:0000": [
                    [
                        -0.43068,
                        0.0,
                        -0.9025,
                        -3.51266
                    ],
                    [
                        0.0,
                        1.0,
                        0.0,
                        0.60867
                    ],
                    [
                        0.9025,
                        0.0,
                        -0.43068,
                        -2.91201
                    ],
                    [
                        0.0,
                        0.0,
                        0.0,
                        1.0
                    ]
                ]
            },
            "markers": [],
            "target_receptacles": [
                [
                    "ccc3a05acbdd0ca79a82f36a71cd775f2781eb62_:0000",
                    null
                ]
            ],
            "goal_receptacles": [
                [
                    "3b77d0a7c6b76e39f050385d2548c0de327b76f2_:0000",
                    null
                ]
            ],
            "name_to_receptacle": {
                "054_softball_:0000": "ccc3a05acbdd0ca79a82f36a71cd775f2781eb62_:0000|receptacle_mesh_ccc3a05acbdd0ca79a82f36a71cd775f2781eb62.0001"
            }
        },
        {
            "episode_id": "1",
            "scene_id": "data/scene_datasets/hssd-hab/scenes-uncluttered/102344529.scene_instance.json",
            "scene_dataset_config": "data/scene_datasets/hssd-hab/hssd-hab-uncluttered.scene_dataset_config.json",
            "additional_obj_config_paths": [
                "data/objects/ycb/configs/",
                "data/replica_cad/configs/objects/"
            ],
            "start_position": [
                0,
                0,
                0
            ],
            "start_rotation": [
                0,
                0,
                0,
                1
            ],
            "info": {
                "object_labels": {
                    "008_pudding_box_:0000": "any_targets|0"
                }
            },
            "ao_states": {},
            "rigid_objs": [
                [
                    "008_pudding_box.object_config.json",
                    [
                        [
                            0.43102,
                            0.27422,
                            0.85967,
                            -6.21769
                        ],
                        [
                            -0.12287,
                            0.96167,
                            -0.24515,
                            0.54409
                        ],
                        [
                            -0.89394,
                            4e-05,
                            0.44819,
                            -4.15175
                        ],
                        [
                            0.0,
                            0.0,
                            0.0,
                            1.0
                        ]
                    ]
                ]
            ],
            "targets": {
                "008_pudding_box_:0000": [
                    [
                        0.99448,
                        0.0,
                        0.10496,
                        4.94594
                    ],
                    [
                        0.0,
                        1.0,
                        0.0,
                        0.67958
                    ],
                    [
                        -0.10496,
                        0.0,
                        0.99448,
                        0.81628
                    ],
                    [
                        0.0,
                        0.0,
                        0.0,
                        1.0
                    ]
                ]
            },
            "markers": [],
            "target_receptacles": [
                [
                    "a8bdceeb3b502b9755a0ec55b776a874d74cd343_:0000",
                    null
                ]
            ],
            "goal_receptacles": [
                [
                    "23434bad597767536e19c5cf37c97bff4bf46bf0_:0003",
                    null
                ]
            ],
            "name_to_receptacle": {
                "008_pudding_box_:0000": "a8bdceeb3b502b9755a0ec55b776a874d74cd343_:0000|receptacle_mesh_a8bdceeb3b502b9755a0ec55b776a874d74cd343.0000"
            }
        },
        {
            "episode_id": "3",
            "scene_id": "data/scene_datasets/hssd-hab/scenes-uncluttered/102344529.scene_instance.json",
            "scene_dataset_config": "data/scene_datasets/hssd-hab/hssd-hab-uncluttered.scene_dataset_config.json",
            "additional_obj_config_paths": [
                "data/objects/ycb/configs/",
                "data/replica_cad/configs/objects/"
            ],
            "start_position": [
                0,
                0,
                0
            ],
            "start_rotation": [
                0,
                0,
                0,
                1
            ],
            "info": {
                "object_labels": {
                    "050_medium_clamp_:0000": "any_targets|0"
                }
            },
            "ao_states": {},
            "rigid_objs": [
                [
                    "050_medium_clamp.object_config.json",
                    [
                        [
                            0.9981,
                            0.0551,
                            0.02746,
                            -10.43867
                        ],
                        [
                            -0.05727,
                            0.99468,
                            0.08569,
                            0.91757
                        ],
                        [
                            -0.02259,
                            -0.0871,
                            0.99594,
                            1.50507
                        ],
                        [
                            0.0,
                            0.0,
                            0.0,
                            1.0
                        ]
                    ]
                ]
            ],
            "targets": {
                "050_medium_clamp_:0000": [
                    [
                        0.98227,
                        0.0,
                        0.18745,
                        -3.33748
                    ],
                    [
                        0.0,
                        1.0,
                        0.0,
                        0.68111
                    ],
                    [
                        -0.18745,
                        0.0,
                        0.98227,
                        -3.74822
                    ],
                    [
                        0.0,
                        0.0,
                        0.0,
                        1.0
                    ]
                ]
            },
            "markers": [],
            "target_receptacles": [
                [
                    "51bf4c899c925cae53ee4d4305ac00beaec03a4b_:0000",
                    null
                ]
            ],
            "goal_receptacles": [
                [
                    "cb0d27b5428679b54fc8bf347ccc168cba08092f_:0000",
                    null
                ]
            ],
            "name_to_receptacle": {
                "050_medium_clamp_:0000": "51bf4c899c925cae53ee4d4305ac00beaec03a4b_:0000|receptacle_mesh_51bf4c899c925cae53ee4d4305ac00beaec03a4b.0000"
            }
        },
        {
            "episode_id": "4",
            "scene_id": "data/scene_datasets/hssd-hab/scenes-uncluttered/102344529.scene_instance.json",
            "scene_dataset_config": "data/scene_datasets/hssd-hab/hssd-hab-uncluttered.scene_dataset_config.json",
            "additional_obj_config_paths": [
                "data/objects/ycb/configs/",
                "data/replica_cad/configs/objects/"
            ],
            "start_position": [
                0,
                0,
                0
            ],
            "start_rotation": [
                0,
                0,
                0,
                1
            ],
            "info": {
                "object_labels": {
                    "055_baseball_:0000": "any_targets|0"
                }
            },
            "ao_states": {},
            "rigid_objs": [
                [
                    "055_baseball.object_config.json",
                    [
                        [
                            0.42745,
                            -0.26033,
                            0.86574,
                            8.83756
                        ],
                        [
                            0.30666,
                            0.94262,
                            0.13204,
                            1.11157
                        ],
                        [
                            -0.85044,
                            0.20905,
                            0.48276,
                            1.16715
                        ],
                        [
                            0.0,
                            0.0,
                            0.0,
                            1.0
                        ]
                    ]
                ]
            ],
            "targets": {
                "055_baseball_:0000": [
                    [
                        0.30332,
                        0.0,
                        -0.95289,
                        5.33452
                    ],
                    [
                        0.0,
                        1.0,
                        0.0,
                        0.69959
                    ],
                    [
                        0.95289,
                        0.0,
                        0.30332,
                        0.77825
                    ],
                    [
                        0.0,
                        0.0,
                        0.0,
                        1.0
                    ]
                ]
            },
            "markers": [],
            "target_receptacles": [
                [
                    "15a81c5727eba4e4a4161e1cf2c76fe2c601ae15_:0000",
                    null
                ]
            ],
            "goal_receptacles": [
                [
                    "23434bad597767536e19c5cf37c97bff4bf46bf0_:0004",
                    null
                ]
            ],
            "name_to_receptacle": {
                "055_baseball_:0000": "15a81c5727eba4e4a4161e1cf2c76fe2c601ae15_:0000|receptacle_mesh_15a81c5727eba4e4a4161e1cf2c76fe2c601ae15.0001"
            }
        }
    ]
}