{
    "config": null,
    "episodes": [
        {
            "episode_id": "0",
            "scene_id": "data/scene_datasets/hssd-hab/scenes-uncluttered/103997970_171031287.scene_instance.json",
            "scene_dataset_config": "data/scene_datasets/hssd-hab/hssd-hab-uncluttered.scene_dataset_config.json",
            "additional_obj_config_paths": [
                "data/objects/ycb/configs/",
                "data/replica_cad/configs/objects/"
            ],
            "start_position": [
                0,
                0,
                0
            ],
            "start_rotation": [
                0,
                0,
                0,
                1
            ],
            "info": {
                "object_labels": {
                    "054_softball_:0000": "any_targets|0"
                }
            },
            "ao_states": {},
            "rigid_objs": [
                [
                    "054_softball.object_config.json",
                    [
                        [
                            -0.40136,
                            -0.59997,
                            -0.69206,
                            -10.50651
                        ],
                        [
                            0.11205,
                            0.71775,
                            -0.68723,
                            0.79535
                        ],
                        [
                            0.90904,
                            -0.35337,
                            -0.22085,
                            -3.71535
                        ],
                        [
                            0.0,
                            0.0,
                            0.0,
                            1.0
                        ]
                    ]
                ]
            ],
            "targets": {
                "054_softball_:0000": [
                    [
                        -0.9343,
                        0.0,
                        0.35648,
                        -4.53262
                    ],
                    [
                        0.0,
                        1.0,
                        0.0,
                        0.46639
                    ],
                    [
                        -0.35648,
                        0.0,
                        -0.9343,
                        -3.83692
                    ],
                    [
                        0.0,
                        0.0,
                        0.0,
                        1.0
                    ]
                ]
            },
            "markers": [],
            "target_receptacles": [
                [
                    "3f9265b5b5e5abd5332ce66078e5eecbc3a9366d_:0000",
                    null
                ]
            ],
            "goal_receptacles": [
                [
                    "4d9190b21102af091661cb3272d0c76fd068daa8_:0000",
                    null
                ]
            ],
            "name_to_receptacle": {
                "054_softball_:0000": "3f9265b5b5e5abd5332ce66078e5eecbc3a9366d_:0000|receptacle_mesh_3f9265b5b5e5abd5332ce66078e5eecbc3a9366d.0000"
            }
        },
        {
            "episode_id": "1",
            "scene_id": "data/scene_datasets/hssd-hab/scenes-uncluttered/103997970_171031287.scene_instance.json",
            "scene_dataset_config": "data/scene_datasets/hssd-hab/hssd-hab-uncluttered.scene_dataset_config.json",
            "additional_obj_config_paths": [
                "data/objects/ycb/configs/",
                "data/replica_cad/configs/objects/"
            ],
            "start_position": [
                0,
                0,
                0
            ],
            "start_rotation": [
                0,
                0,
                0,
                1
            ],
            "info": {
                "object_labels": {
                    "042_adjustable_wrench_:0000": "any_targets|0"
                }
            },
            "ao_states": {},
            "rigid_objs": [
                [
                    "042_adjustable_wrench.object_config.json",
                    [
                        [
                            0.42262,
                            -0.04939,
                            -0.90496,
                            -10.45579
                        ],
                        [
                            0.05359,
                            0.99813,
                            -0.02944,
                            0.76037
                        ],
                        [
                            0.90472,
                            -0.03605,
                            0.42448,
                            -3.8522
                        ],
                        [
                            0.0,
                            0.0,
                            0.0,
                            1.0
                        ]
                    ]
                ]
            ],
            "targets": {
                "042_adjustable_wrench_:0000": [
                    [
                        0.94238,
                        0.0,
                        -0.33454,
                        -4.37729
                    ],
                    [
                        0.0,
                        1.0,
                        0.0,
                        0.93605
                    ],
                    [
                        0.33454,
                        0.0,
                        0.94238,
                        -6.34914
                    ],
                    [
                        0.0,
                        0.0,
                        0.0,
                        1.0
                    ]
                ]
            },
            "markers": [],
            "target_receptacles": [
                [
                    "3f9265b5b5e5abd5332ce66078e5eecbc3a9366d_:0000",
                    null
                ]
            ],
            "goal_receptacles": [
                [
                    "0ad85902da0211d4439630d8f217340abdcfff2d_:0000",
                    null
                ]
            ],
            "name_to_receptacle": {
                "042_adjustable_wrench_:0000": "3f9265b5b5e5abd5332ce66078e5eecbc3a9366d_:0000|receptacle_mesh_3f9265b5b5e5abd5332ce66078e5eecbc3a9366d.0000"
            }
        },
        {
            "episode_id": "2",
            "scene_id": "data/scene_datasets/hssd-hab/scenes-uncluttered/103997970_171031287.scene_instance.json",
            "scene_dataset_config": "data/scene_datasets/hssd-hab/hssd-hab-uncluttered.scene_dataset_config.json",
            "additional_obj_config_paths": [
                "data/objects/ycb/configs/",
                "data/replica_cad/configs/objects/"
            ],
            "start_position": [
                0,
                0,
                0
            ],
            "start_rotation": [
                0,
                0,
                0,
                1
            ],
            "info": {
                "object_labels": {
                    "010_potted_meat_can_:0000": "any_targets|0"
                }
            },
            "ao_states": {},
            "rigid_objs": [
                [
                    "010_potted_meat_can.object_config.json",
                    [
                        [
                            0.88091,
                            0.05133,
                            0.47049,
                            -4.97482
                        ],
                        [
                            -0.0645,
                            0.99785,
                            0.0119,
                            0.48623
                        ],
                        [
                            -0.46887,
                            -0.04083,
                            0.88232,
                            -3.53516
                        ],
                        [
                            0.0,
                            0.0,
                            0.0,
                            1.0
                        ]
                    ]
                ]
            ],
            "targets": {
                "010_potted_meat_can_:0000": [
                    [
                        0.83806,
                        0.0,
                        0.54557,
                        -5.79424
                    ],
                    [
                        0.0,
                        1.0,
                        0.0,
                        0.91583
                    ],
                    [
                        -0.54557,
                        0.0,
                        0.83806,
                        -0.86744
                    ],
                    [
                        0.0,
                        0.0,
                        0.0,
                        1.0
                    ]
                ]
            },
            "markers": [],
            "target_receptacles": [
                [
                    "4d9190b21102af091661cb3272d0c76fd068daa8_:0000",
                    null
                ]
            ],
            "goal_receptacles": [
                [
                    "3aef5476fb1c9b2f3cae1b2ca8b33c1bae7ec1d2_:0000",
                    null
                ]
            ],
            "name_to_receptacle": {
                "010_potted_meat_can_:0000": "4d9190b21102af091661cb3272d0c76fd068daa8_:0000|receptacle_mesh_4d9190b21102af091661cb3272d0c76fd068daa8.0009"
            }
        },
        {
            "episode_id": "3",
            "scene_id": "data/scene_datasets/hssd-hab/scenes-uncluttered/103997970_171031287.scene_instance.json",
            "scene_dataset_config": "data/scene_datasets/hssd-hab/hssd-hab-uncluttered.scene_dataset_config.json",
            "additional_obj_config_paths": [
                "data/objects/ycb/configs/",
                "data/replica_cad/configs/objects/"
            ],
            "start_position": [
                0,
                0,
                0
            ],
            "start_rotation": [
                0,
                0,
                0,
                1
            ],
            "info": {
                "object_labels": {
                    "009_gelatin_box_:0000": "any_targets|0"
                }
            },
            "ao_states": {},
            "rigid_objs": [
                [
                    "009_gelatin_box.object_config.json",
                    [
                        [
                            -0.80471,
                            0.10674,
                            0.58399,
                            -5.56334
                        ],
                        [
                            0.07385,
                            0.99406,
                            -0.07993,
                            0.46449
                        ],
                        [
                            -0.58906,
                            -0.02119,
                            -0.80781,
                            -3.42191
                        ],
                        [
                            0.0,
                            0.0,
                            0.0,
                            1.0
                        ]
                    ]
                ]
            ],
            "targets": {
                "009_gelatin_box_:0000": [
                    [
                        0.29736,
                        0.0,
                        0.95477,
                        -7.29003
                    ],
                    [
                        0.0,
                        1.0,
                        0.0,
                        0.4652
                    ],
                    [
                        -0.95477,
                        0.0,
                        0.29736,
                        -2.99925
                    ],
                    [
                        0.0,
                        0.0,
                        0.0,
                        1.0
                    ]
                ]
            },
            "markers": [],
            "target_receptacles": [
                [
                    "4d9190b21102af091661cb3272d0c76fd068daa8_:0000",
                    null
                ]
            ],
            "goal_receptacles": [
                [
                    "7ebbcee61f6f7b26bf9b346ac960fd0248fc2bdd_:0000",
                    null
                ]
            ],
            "name_to_receptacle": {
                "009_gelatin_box_:0000": "4d9190b21102af091661cb3272d0c76fd068daa8_:0000|receptacle_mesh_4d9190b21102af091661cb3272d0c76fd068daa8.0005"
            }
        }
    ]
}